{
  "0": "",
  "1000": "低语河谷",
  "1001": "罗塔诺海（船首）",
  "1002": "罗塔诺海（船尾）",
  "1003": "库尔札斯不冻池",
  "1004": "清澈池",
  "1005": "灾祸池南",
  "1006": "灾祸池西",
  "1007": "彻悟岩窟西",
  "1008": "沙利亚克河上流",
  "1009": "沙利亚克河中流",
  "101": "常影区",
  "1010": "索姆阿尔云帽",
  "1011": "废液池",
  "1012": "石绿湖西北岸",
  "1013": "永夏岛北",
  "1014": "提蒙河",
  "1015": "昏暗林",
  "1016": "流星尾",
  "1017": "威罗迪纳河",
  "1018": "幻河",
  "1019": "夫妇池",
  "1020": "慢水涤",
  "1021": "石楠瀑布",
  "1022": "判官神像",
  "1023": "猛牛浴池",
  "1025": "赎罪之腕",
  "1026": "盐湖",
  "1027": "红玉炮台近海",
  "1028": "狱之盖近海",
  "1029": "龟甲岛近海",
  "1030": "冲之岩近海",
  "1031": "自凝岛近海",
  "1032": "渔村沿岸",
  "1033": "绝鬼岛近海",
  "1034": "苍鹭池",
  "1035": "苍鹭河",
  "1036": "茨菰村水塘",
  "1037": "多玛城前",
  "1038": "城下码头",
  "1039": "无二江东",
  "104": "萌芽池",
  "1040": "无二江西",
  "1041": "梅泉乡",
  "1042": "七彩沟",
  "1043": "七彩溪谷",
  "1044": "朵塔儿水洲",
  "1045": "太阳湖",
  "1046": "涅木卡勒河",
  "1047": "塔奥卡勒河",
  "1048": "亚特卡勒河下游",
  "1049": "亚特卡勒河上游",
  "112": "十二神大圣堂",
  "126": "蔓根沼",
  "155": "花蜜栈桥",
  "168": "接雨草树林",
  "174": "橡树原",
  "182": "无赖川",
  "192": "轻声谷",
  "193": "尼姆河",
  "197": "遗孀泪",
  "2004": "荒烟野地",
  "2008": "彻悟岩窟",
  "2013": "招恶荒岛",
  "2014": "人王遗迹",
  "2017": "绿茵岛",
  "2019": "悲叹飞泉",
  "202": "盲铁坑道",
  "2020": "宽慰河",
  "2029": "饵食台地",
  "2030": "光轮祭坛",
  "2035": "湍流三角地",
  "2039": "沙利亚克河",
  "2048": "惋惜之晶遗迹",
  "206": "太阳海岸",
  "2064": "不洁古像",
  "2079": "西方水泉",
  "2102": "云顶",
  "2103": "沃仙曦染",
  "2105": "蓝天窗",
  "2109": "阿尔法管区",
  "211": "隐秘瀑布",
  "2112": "德尔塔管区",
  "2113": "生态园",
  "2114": "阿济兹拉旗舰岛",
  "2120": "云水塘",
  "2129": "魔窟离岛",
  "214": "红螳螂瀑布",
  "2173": "冠毛大树",
  "2177": "超星际通信塔",
  "218": "雨燕塔殖民地",
  "220": "酿酒师灯塔",
  "2201": "交汇河",
  "2211": "灰烬池",
  "2217": "灰尾瀑布",
  "2227": "龙涎",
  "2257": "云冠涌泉",
  "2258": "云冠洞穴",
  "2259": "云冠西南池",
  "2260": "云冠鱼洞",
  "2261": "云冠西北池",
  "2262": "狂风云海",
  "2263": "无风云海",
  "2264": "旋风云海",
  "228": "船舶墓场",
  "234": "愚者瀑布",
  "245": "足迹谷",
  "246": "西风岬",
  "249": "执掌峡谷",
  "2500": "哈克卡勒河",
  "2501": "防波堤",
  "2502": "幻河上游",
  "2503": "星导寺入口",
  "2504": "神拳痕",
  "2505": "白银乡",
  "2506": "白银水路",
  "2507": "多玛飞地",
  "253": "火墙",
  "264": "丰饶神井",
  "266": "白银集市",
  "272": "月牙湾",
  "274": "黄昏湾",
  "275": "月滴洞",
  "276": "帕拉塔安息地",
  "28": "利姆萨·罗敏萨上层甲板",
  "29": "利姆萨·罗敏萨下层甲板",
  "297": "邪嗣",
  "308": "宇格拉姆河",
  "314": "火蜥蜴河",
  "323": "遗忘绿洲",
  "3289": "三艺区",
  "3290": "四艺区",
  "3291": "水晶都起居室",
  "3292": "风化裂痕",
  "3293": "锈迹贮水池",
  "3294": "始源湖",
  "3295": "阴沉乡",
  "3296": "贤岛",
  "3297": "沃茨河上游",
  "3298": "白油瀑布",
  "3299": "沃茨河下游",
  "330": "青磷泉",
  "3300": "刺舌滴",
  "3301": "珂露西亚岛西海岸",
  "3302": "观海湾",
  "3303": "珂露西亚岛东海岸",
  "3304": "废船街",
  "3305": "沙河",
  "3306": "拿巴示断绝",
  "3307": "琥珀丘",
  "3308": "手镜湖",
  "3309": "身镜湖",
  "3310": "傲慢的年长溪流",
  "3311": "嫉妒的年少溪流",
  "3312": "宠坏的年幼溪流",
  "3313": "圣法斯里克天庭",
  "3314": "科拉德排水沟",
  "3315": "蛇水湖",
  "3316": "血盅",
  "3317": "洛查特尔河",
  "3318": "缪栎的乡愁南部",
  "3319": "结誓洞窟",
  "3320": "鳎沙地窖",
  "3321": "陆人墓标",
  "3322": "卡利班深海峡西北",
  "3323": "卡利班古巢西",
  "3324": "卡利班古巢东",
  "3325": "尊紫洞",
  "3326": "诺弗兰特大陆坡",
  "337": "莫拉比造船厂",
  "338": "砂盐滩",
  "339": "守炬埠头",
  "340": "空心穴",
  "341": "奥修昂火炬",
  "3448": "加拉迪翁湾外海",
  "3449": "加拉迪翁湾外海幻海流",
  "3450": "梅尔托尔海峡南",
  "3451": "梅尔托尔海峡南幻海流",
  "3452": "梅尔托尔海峡北",
  "3453": "梅尔托尔海峡北幻海流",
  "3454": "罗塔诺海海面",
  "3455": "罗塔诺海海面幻海流",
  "3458": "缪栎之泪",
  "3489": "摇风云海",
  "3532": "息风云海",
  "3533": "烈风云海",
  "3621": "谢尔达莱群岛近海",
  "3622": "谢尔达莱群岛近海幻海流",
  "3623": "绯汐海近海",
  "3624": "绯汐海近海幻海流",
  "3625": "罗斯利特湾近海",
  "3626": "罗斯利特湾近海幻海流",
  "363": "萨普沙产卵地",
  "365": "隐秘港",
  "389": "落魔崖",
  "392": "圣人泪",
  "398": "圣人旅道",
  "404": "披雪大冰壁",
  "4050": "知识神海港",
  "4051": "碧谷",
  "4052": "沉思泉",
  "4053": "一号天球口",
  "4054": "一号沟渠",
  "4055": "二号天球口",
  "4056": "二号沟渠",
  "4057": "深壕",
  "4058": "云使飞沫",
  "4059": "新港沿岸",
  "4060": "萨维奈岛近海",
  "4061": "代米尔遗烈乡沿岸",
  "4062": "巨胆石采掘场",
  "4063": "塔门",
  "4064": "乳河",
  "4065": "帕瓦纳的悔悟",
  "4066": "摩耶幻泉",
  "4067": "熏香海岸",
  "4068": "艾布拉纳不冻池",
  "4069": "洁白环濠",
  "4070": "最伟大的森林",
  "4071": "荧光池",
  "4072": "冻土裂痕",
  "4073": "逍遥水径",
  "4074": "翠牙园下层",
  "4075": "忘海",
  "4076": "沼癸辛γ",
  "4077": "沼癸辛β",
  "4078": "沼癸辛α",
  "4079": "逡巡泉",
  "4080": "异亚村落",
  "4081": "湖癸辛",
  "4082": "湖丙α",
  "4083": "湖丙β",
  "410": "银泪湖北岸",
  "413": "纠缠沼泽林",
  "414": "早霜顶",
  "417": "歌咏裂谷",
  "4191": "至福乐土农业区",
  "4192": "至福乐土海洋区α",
  "4193": "至福乐土海洋区β",
  "4194": "至福乐土游乐区α",
  "4195": "至福乐土游乐区β",
  "425": "海雾村",
  "426": "薰衣草苗圃",
  "427": "高脚孤丘",
  "4367": "妖歌海海面",
  "4368": "妖歌海海面幻海流",
  "4369": "黄金港近海",
  "4370": "黄金港近海幻海流",
  "4371": "红玉海海面",
  "4372": "红玉海海面幻海流",
  "4373": "无二江下游",
  "4374": "无二江下游幻海流",
  "5037": "休喙泉",
  "5038": "船头小屋",
  "5039": "满潮港",
  "5040": "沉星浮泪的池",
  "5041": "其瓦固盐池",
  "5042": "卡瓦胡湖",
  "5043": "水没羽毛树林",
  "5044": "哈努水边",
  "5045": "活船水路下游",
  "5046": "露草河岸",
  "5047": "水果岸边",
  "5048": "大舌头瀑布潭",
  "5049": "活船水路上游",
  "5050": "虹彩水底",
  "5051": "钓神基富天坑",
  "5052": "红豹村蓄水池",
  "5053": "蓝咬鹃天坑",
  "5054": "赤血天坑",
  "5055": "白烬天坑",
  "5056": "足尖小坑",
  "5057": "战地天坑",
  "5058": "抱拥天坑",
  "5059": "甜水泉",
  "5060": "涩水天坑",
  "5061": "冥境天坑",
  "5062": "尼葵瑞皮河",
  "5063": "特利湖",
  "5064": "佐戈海峡西侧",
  "5065": "佐戈海峡东侧",
  "5066": "边郊镇壕沟",
  "5067": "终流地",
  "5068": "带雷危险水域",
  "5069": "亚历山德里亚废墟",
  "5070": "居住区域",
  "5071": "易知区",
  "5072": "亩鼠水泉",
  "5073": "地场节点·风",
  "5074": "运河镇南侧",
  "5075": "运河镇北侧",
  "5076": "原型亚历山德里亚",
  "5206": "储泪池",
  "5207": "北侧小跳印记",
  "5208": "西侧小跳印记",
  "5209": "基地东南水池",
  "5210": "空葫芦港",
  "5211": "砷海",
  "5212": "阿尔法闪亮池",
  "5213": "贝塔闪亮池",
  "5214": "月底魔泉瀑布",
  "5286": "退火洞",
  "5287": "玻璃匠基地西侧",
  "5288": "蛋白石十字口",
  "5289": "碱石灰河上游",
  "5290": "碱石灰河中游北侧",
  "5291": "碱石灰河中游南侧",
  "5292": "碱石灰河下游",
  "5293": "沉彩沙坑",
  "5294": "胶囊池",
  "5295": "泡泡地狱",
  "5296": "熔火涌流",
  "59": "静语庄园",
  "82": "兀尔德恩惠地",
  "86": "荣耀溪",
  "950": "未知钓场",
  "951": "叶脉水系",
  "952": "镜池",
  "953": "落翠底",
  "954": "涟漪小川",
  "955": "妖精领溪谷",
  "956": "哈希瓦河上游",
  "957": "哈希瓦河中游",
  "958": "哈希瓦河下游",
  "959": "哈希瓦河东支流",
  "960": "哥布林血流",
  "961": "嘈杂川",
  "962": "秋瓜湖畔",
  "963": "塔赫托特尔湖",
  "964": "翡翠湖滨",
  "965": "红茶川水系下游",
  "966": "纠缠沼泽林源流",
  "967": "歌咏裂谷北部",
  "968": "库尔札斯河",
  "969": "剑峰山麓",
  "970": "巨龙首营地水库",
  "971": "调查队冰洞",
  "972": "伊修加德大云海",
  "973": "和风流地沿岸",
  "974": "盛夏滩沿岸",
  "975": "西永恒川",
  "976": "莫拉比湾西岸",
  "977": "雪松原沿岸地",
  "978": "南鲜血滨",
  "979": "北鲜血滨",
  "980": "东永恒川",
  "981": "接雨草沼泽地",
  "982": "骷髅谷沿岸地",
  "983": "二分石沿岸地",
  "984": "幻影群岛北岸",
  "985": "幻影群岛南岸",
  "987": "石绿湖东北岸",
  "988": "石绿湖浅滩",
  "989": "登天路溪谷",
  "990": "污流上游",
  "991": "污流下游",
  "992": "枯骨北泉",
  "993": "枯骨南泉",
  "995": "不悔战泉",
  "996": "撒沟厉沙海",
  "997": "撒沟厉沙丘",
  "998": "蓝雾涌泉",
  "999": "红茶川水系上游"
}